{
  "db_user":"pdadmin",
  "db_password":"R8$7Zo319%0tUi",
  "db_url":"jdbc:mysql://rm-2zefoq89s74i5bfal.mysql.rds.aliyuncs.com:3306/yw_bus",
  "table_name":"gxxm_a_user",
  "mapping":
      {
        "user_id"           :"user_id",
        "product_id"        :"'111307'",
        "company"           :"'450000001'",
        "reg_name"          :"",
        "nick_name"         :"name",
        "real_name"         :"name",
        "phone"             :"",
        "email"             :"",
        "sex"               :"",
        "birthday"          :"",
        "address"           :"",
        "org_id"            :"org_id",
        "user_type"         :"user_type",
        "first_access_time" :"concat(unix_timestamp(s_create_time,'yyyy-MM-dd HH:mm:ss'),'000')",
        "last_access_time"  :"concat(unix_timestamp(s_create_time,'yyyy-MM-dd HH:mm:ss'),'000')",
        "last_access_ip"    :"",
        "country"           :"'中国'",
        "province"          :"'广西'",
        "city"              :"",
        "location"          :"",
        "row_timestamp"     :"'1603089840000'",
        "row_status"        :"'1'",
        "put_date"          :"'20190006'"
      },
  "partitionsByKey":"DATE_FORMAT(s_create_time,'%d')"
}